{
  "title": "GeoGebra 3D",
  "description": "Graph 3D functions, plot surfaces and do 3D geometry with our free 3D Grapher",
  "majorVersion": 1,
  "minorVersion": 0,
  "patchVersion": 2,
  "runnable": 1,
  "author": "Ahmad Mukhtar",
  "license": "cc-by-sa",
  "machineName": "H5P.GeoGebra3d",
  "coreApi": {
    "majorVersion": 1,
    "minorVersion": 0
  },
  "preloadedJs": [
    {
      "path": "scripts/deployggb.js"
    },
    {
      "path": "scripts/geogebra.js"
    }
  ],
  "preloadedCss": [
    {
      "path": "styles/geogebra.css"
    }
  ],
  "preloadedDependencies": [
    {
      "machineName": "H5P.JoubelUI",
      "majorVersion": 1,
      "minorVersion": 3
    }
  ],
  "editorDependencies": [
    {
      "machineName": "H5PEditor.GeoGebra3DWidget",
      "majorVersion": 1,
      "minorVersion": 0
    }
    ]
}
